PAOFLOW/ACBN0.py
PAOFLOW/DataController.py
PAOFLOW/ErrorHandler.py
PAOFLOW/GPAO.py
PAOFLOW/PAOFLOW.py
PAOFLOW/__init__.py
PAOFLOW/defs/TauModel.py
PAOFLOW/defs/__init__.py
PAOFLOW/defs/add_ext_field.py
PAOFLOW/defs/clebsch_gordan.py
PAOFLOW/defs/communication.py
PAOFLOW/defs/constants.py
PAOFLOW/defs/cuda_fft.py
PAOFLOW/defs/do_Boltz_tensors.py
PAOFLOW/defs/do_Efermi.py
PAOFLOW/defs/do_Hall.py
PAOFLOW/defs/do_adaptive_smearing.py
PAOFLOW/defs/do_atwfc_proj.py
PAOFLOW/defs/do_band_curvature.py
PAOFLOW/defs/do_bands.py
PAOFLOW/defs/do_berry_phase.py
PAOFLOW/defs/do_build_pao_hamiltonian.py
PAOFLOW/defs/do_d2Hd2k.py
PAOFLOW/defs/do_dipole.py
PAOFLOW/defs/do_doping.py
PAOFLOW/defs/do_dos.py
PAOFLOW/defs/do_double_grid.py
PAOFLOW/defs/do_doubling.py
PAOFLOW/defs/do_effective_mass.py
PAOFLOW/defs/do_eigh.py
PAOFLOW/defs/do_epsilon.py
PAOFLOW/defs/do_fermisurf.py
PAOFLOW/defs/do_find_Weyl.py
PAOFLOW/defs/do_gradient.py
PAOFLOW/defs/do_ipr.py
PAOFLOW/defs/do_minimal.py
PAOFLOW/defs/do_momentum.py
PAOFLOW/defs/do_non_ortho.py
PAOFLOW/defs/do_ortho.py
PAOFLOW/defs/do_pdos.py
PAOFLOW/defs/do_projectability.py
PAOFLOW/defs/do_rashba_edelstein.py
PAOFLOW/defs/do_real_space.py
PAOFLOW/defs/do_spin_orbit.py
PAOFLOW/defs/do_spin_texture.py
PAOFLOW/defs/do_tau_models.py
PAOFLOW/defs/do_topology.py
PAOFLOW/defs/do_transport.py
PAOFLOW/defs/do_wave_function_site_projection.py
PAOFLOW/defs/file_io.py
PAOFLOW/defs/get_K_grid_fft.py
PAOFLOW/defs/get_R_grid_fft.py
PAOFLOW/defs/header.py
PAOFLOW/defs/kpnts_interpolation_mesh.py
PAOFLOW/defs/models.py
PAOFLOW/defs/module_prerequisites.py
PAOFLOW/defs/pao_sym.py
PAOFLOW/defs/perturb_split.py
PAOFLOW/defs/pfaffian.py
PAOFLOW/defs/plot_compare_PAO_DFT_eigs.py
PAOFLOW/defs/pyints.py
PAOFLOW/defs/read_QE_xml.py
PAOFLOW/defs/read_VASP.py
PAOFLOW/defs/read_inputfile_xml_parse.py
PAOFLOW/defs/read_pao_output.py
PAOFLOW/defs/read_sh_nl.py
PAOFLOW/defs/read_upf.py
PAOFLOW/defs/report_exception.py
PAOFLOW/defs/smearing.py
PAOFLOW/defs/upf_gaussfit.py
paoflow-2.2.3.dist-info/METADATA
paoflow-2.2.3.dist-info/WHEEL
paoflow-2.2.3.dist-info/top_level.txt
paoflow-2.2.3.dist-info/RECORD
