Metadata-Version: 2.1
Name: paoflow
Version: 2.2.3
Summary: Utility to construct and operate on Hamiltonians from the Projections of DFT wfc on Atomic Orbital bases (PAO)
Home-page: https://github.com/marcobn/PAOFLOW
Author: Marco Buongiorno Nardelli
Author-email: mbn@unt.edu
Platform: Linux
Requires-Python: >=3.6
Requires-Dist: numpy
Requires-Dist: scipy
Provides-Extra: graphics
Requires-Dist: matplotlib ; extra == 'graphics'
Requires-Dist: vtk ; extra == 'graphics'
Provides-Extra: weyl_search
Requires-Dist: z2pack ; extra == 'weyl_search'
Requires-Dist: tbmodels ; extra == 'weyl_search'
